Metadata-Version: 2.1
Name: BlaguesApi
Version: 0.10
Summary: Python API wrapper for BlaguesAPI.fr
Home-page: https://github.com/coco875/BlagueAPI
Author: coco875
Author-email: pereira.jannin@gmail.com
License: MIT
Download-URL: https://github.com/coco875/BlagueAPI/archive/refs/tags/v_09.tar.gz
Keywords: API,Joke,French
Platform: UNKNOWN
Classifier: Development Status :: 4 - Beta
Classifier: Intended Audience :: Developers
Classifier: Topic :: Software Development :: Build Tools
Classifier: License :: OSI Approved :: MIT License
Classifier: Programming Language :: Python :: 3
Classifier: Programming Language :: Python :: 3.4
Classifier: Programming Language :: Python :: 3.5
Classifier: Programming Language :: Python :: 3.6
Classifier: Programming Language :: Python :: 3.7
Classifier: Programming Language :: Python :: 3.8
Requires-Python: >=3.6
